venv_pack/__init__.py
venv_pack/__main__.py
venv_pack/_version.py
venv_pack/core.py
venv_pack/formats.py
venv_pack/progress.py
venv_pack/scripts/CPYTHON_LICENSE.txt
venv_pack/scripts/common/activate
venv_pack-0.2.0.dist-info/METADATA
venv_pack-0.2.0.dist-info/RECORD
venv_pack-0.2.0.dist-info/WHEEL
venv_pack-0.2.0.dist-info/entry_points.txt
venv_pack-0.2.0.dist-info/top_level.txt
