Metadata-Version: 1.2
Name: venv-pack
Version: 0.2.0
Summary: Package virtual environments for redistribution
Home-page: https://jcrist.github.io/venv-pack/
Maintainer: Jim Crist
Maintainer-email: jiminy.crist@gmail.com
License: BSD
Project-URL: Source Code, https://github.com/jcrist/venv-pack/
Keywords: venv packaging
Platform: UNKNOWN
Classifier: Development Status :: 4 - Beta
Classifier: License :: OSI Approved :: BSD License
Classifier: Programming Language :: Python :: 2.7
Classifier: Programming Language :: Python :: 3.5
Classifier: Programming Language :: Python :: 3.6
Classifier: Programming Language :: Python :: 3.7
Classifier: Topic :: System :: Archiving :: Packaging
Classifier: Topic :: System :: Software Distribution
Classifier: Topic :: Software Development :: Build Tools
